{
    "texture": {
        "vars:DISPLAY" : {
            "false" : {
                "vars:ANIM1_BASE": {
                    "true" : "transertx"
                },
                "vars:ANIM1_SHORT": {
                    "true" : "shorttx"
                },
                "vars:ANIM1_SWIMSUIT": {
                    "true" : "swimsuittx"
                },
                "vars:ANIM1_NORMAL": {
                    "true" : "normaltx"
                },
                "vars:ANIM2": {
                    "true" : "suit"
                }
            },
            "true" : "transer"
        },
        
        "vars:TRANSFORMED" : {
            "true" : "base"
        },
        "vars:NORMAL" : {
            "true" : {
                "vars:VISUALIZER":{
                    "false" : "visualizer_up_normal",
                    "true" : "visualizer_down_normal"
                }
            }
        },
        "vars:SWIMSUIT" : {
            "true" : {
                "vars:VISUALIZER":{
                    "false" : "visualizer_up_swimsuit",
                    "true" : "visualizer_down_swimsuit"
                }
            }
        },
        "vars:SHORT" : {
            "true" : {
                "vars:VISUALIZER":{
                    "false" : "visualizer_up_short",
                    "true" : "visualizer_down_short"
                }
            }
        },
        "vars:BASE" : {
            "true" : {
                "vars:VISUALIZER":{
                    "false" : "visualizer_up",
                    "true" : "visualizer_down"
                }
            }
        },

        "default": "null"
    },
        
      "showModel": {

        "head": ["CHESTPLATE"],

        "headwear": ["CHESTPLATE"],

        "body": ["CHESTPLATE"],

        "rightArm": ["CHESTPLATE"],

        "leftArm": ["CHESTPLATE"],

        "rightLeg": ["CHESTPLATE"],

        "leftLeg": ["CHESTPLATE"]

      },
    
    "fixHatLayer": ["CHESTPLATE"],
        
    "lights" : {
        "vars:DISPLAY" : {
            "false" : {
                "vars:OPEN" : {
                    "true":{
                        "vars:VISUALIZER":{
                            "false" : "visualizer_up_lights",
                            "true" : "visualizer_down_lights"
                        }
                    }
                },
                "vars:ANIM": {
                    "true" : "suit_lights"
                }
            },
            "true" : "transer_lights"
        },

        "vars:TRANSFORMED" : {
            "true" : "lights"
        },

        "default": "null"
    },
    
  "custom": {
      
    "fiskheroes:animation": {
      "animation": "skyhighheroes:stelar_flight",
      "data": "fiskheroes:glide_flying_timer"
    },
      
    "fiskheroes:ears": {
      "applicable": ["CHESTPLATE"],
      "angle": 7.5,
      "inset": -0.02
    },
    
    "fiskheroes:invisibility": {
      "applicable": ["CHESTPLATE"],
      "includeEffects": ["fiskheroes:shield", "fiskheroes:ears", "fiskheroes:beam|headStart", "fiskheroes:beam|bodyStart", "fiskheroes:beam|armsStart", "fiskheroes:beam|armRightStart", "fiskheroes:beam|armLeftStart", "fiskheroes:beam|legsStart", "fiskheroes:beam|omegaXis"],
      "opacityMin": 0.0,
      "opacityMax": 1.0,
      "data": "fiskheroes:teleport_timer"
    },
    
    "fiskheroes:shield|blade": {

      "applicable": ["CHESTPLATE"],

      "texture": ["null", "blade"],

      "offset": [1.5, 8.0, 0.0],

      "rotation": [0.0, 0.0, 0.0],

      "curve": [0.0, 0.0],

      "mirror": false,

      "large": true,

      "data": "0 + (entity.getHeldItem().isEmpty() && entity.getData('skyhighheroes:dyn/battle_card') == 2)"

    },
    
    "fiskheroes:shield|cannon1": {

      "applicable": ["CHESTPLATE"],

      "texture": ["cannon_right", "cannon_right_lights"],

      "offset": [1.0, 7.0, 3.0],

      "rotation": [0.0, 90.0, 0.0],

      "curve": [0.0, 0.0],

      "mirror": false,

      "large": true,

      "data": "(2.5 * (entity.getInterpolatedData('skyhighheroes:dyn/wave_changing_timer') - 0.6)) - (!entity.getHeldItem().isEmpty() || entity.getData('skyhighheroes:dyn/battle_card') == 2)"

    },

    "fiskheroes:shield|cannon2": {

      "applicable": ["CHESTPLATE"],

      "texture": ["cannon_left", "cannon_left_lights"],

      "offset": [1.0, 7.0, -3.0],

      "rotation": [0.0, -90.0, 0.0],

      "curve": [0.0, 0.0],

      "mirror": false,

      "large": true,

      "data": "(2.5 * (entity.getInterpolatedData('skyhighheroes:dyn/wave_changing_timer') - 0.6)) - (!entity.getHeldItem().isEmpty() || entity.getData('skyhighheroes:dyn/battle_card') == 2)"

    },
    
    "fiskheroes:shield|cannon3": {

      "applicable": ["CHESTPLATE"],

      "texture": ["cannon_top", "null"],

      "offset": [4.0, 7.0, 0.0],

      "rotation": [0.0, 0.0, 0.0],

      "curve": [0.0, 0.0],

      "mirror": false,

      "large": true,

      "data": "(2.5 * (entity.getInterpolatedData('skyhighheroes:dyn/wave_changing_timer') - 0.6)) - (!entity.getHeldItem().isEmpty() || entity.getData('skyhighheroes:dyn/battle_card') == 2)"

    },
    
    "fiskheroes:shield|cannon4": {

      "applicable": ["CHESTPLATE"],

      "texture": ["cannon_bottom", "null"],

      "offset": [-2.0, 7.0, 0.0],

      "rotation": [0.0, 180.0, 0.0],

      "curve": [0.0, 0.0],

      "mirror": false,

      "large": true,

      "data": "(2.5 * (entity.getInterpolatedData('skyhighheroes:dyn/wave_changing_timer') - 0.6)) - (!entity.getHeldItem().isEmpty() || entity.getData('skyhighheroes:dyn/battle_card') == 2)"

    },
    
    "fiskheroes:shield|cannon5": {

      "applicable": ["CHESTPLATE"],

      "texture": ["cannon_front", "null"],

      "offset": [3.0, 12.0, 0.0],

      "rotation": [0.0, 0.0, -90.0],

      "curve": [0.0, 0.0],

      "mirror": false,

      "large": true,

      "data": "(2.5 * (entity.getInterpolatedData('skyhighheroes:dyn/wave_changing_timer')) - 0.6)) - (!entity.getHeldItem().isEmpty() || entity.getData('skyhighheroes:dyn/battle_card') == 2)"

    },
    "fiskheroes:shield|hair": {

      "applicable": ["CHESTPLATE"],
      
      "anchor" : "head",

      "texture": ["hair", "null"],

      "offset": [0.0, -11.0625, 2.0625],

      "rotation": [0.0, 180.0, 0.0],

      "curve": [0.0, 0.0],

      "mirror": false,

      "large": true,

      "data": "Math.min(Math.max(entity.getInterpolatedData('skyhighheroes:dyn/wave_changing_timer') < 0.5 ? (((-81/16) * entity.getInterpolatedData('skyhighheroes:dyn/wave_changing_timer')) + (50/32)) : (((162/16) * entity.getInterpolatedData('skyhighheroes:dyn/wave_changing_timer')) - (284/32)), 0.0), 1.0) - entity.isDisplayStand()"

    }
  },
  
  "vars": {
      "ANIM": "entity.getData('skyhighheroes:dyn/wave_changing_timer') < 1 && entity.getData('skyhighheroes:dyn/wave_changing_timer') > 0",
        "ANIM1": "(entity.getData('skyhighheroes:dyn/wave_changing_timer') < 0.5 && entity.getData('skyhighheroes:dyn/wave_changing_timer') > 0)",
        "ANIM1_BASE": "entity.getData('skyhighheroes:dyn/stelar_clothes') == 0 && (entity.getData('skyhighheroes:dyn/wave_changing_timer') < 0.5 && entity.getData('skyhighheroes:dyn/wave_changing_timer') > 0)",
        "ANIM1_SHORT": "entity.getData('skyhighheroes:dyn/stelar_clothes') == 1 && (entity.getData('skyhighheroes:dyn/wave_changing_timer') < 0.5 && entity.getData('skyhighheroes:dyn/wave_changing_timer') > 0)",
        "ANIM1_SWIMSUIT": "entity.getData('skyhighheroes:dyn/stelar_clothes') == 2 && (entity.getData('skyhighheroes:dyn/wave_changing_timer') < 0.5 && entity.getData('skyhighheroes:dyn/wave_changing_timer') > 0)",
        "ANIM1_NORMAL": "entity.getData('skyhighheroes:dyn/stelar_clothes') == 3 && (entity.getData('skyhighheroes:dyn/wave_changing_timer') < 0.5 && entity.getData('skyhighheroes:dyn/wave_changing_timer') > 0)",
        "ANIM2": "entity.getData('skyhighheroes:dyn/wave_changing_timer') < 1 && entity.getData('skyhighheroes:dyn/wave_changing_timer') >= 0.5",
        "OPEN": "entity.getData('skyhighheroes:dyn/wave_changing_timer') == 0",
        "ANIM_FULL": "entity.getData('skyhighheroes:dyn/wave_changing_timer') > 0",
    "TRANSFORMED": "entity.getData('skyhighheroes:dyn/wave_changing_timer') == 1",
        "VISUALIZER": "entity.getData('skyhighheroes:dyn/visualizer') == 1",
    "GLIDING" : "entity.getData('fiskheroes:glide_flying_timer') == 1 && entity.getData('fiskheroes:jetpacking_timer') == 1",
        "BASE" : "entity.getData('skyhighheroes:dyn/stelar_clothes') == 0",
        "SHORT" : "entity.getData('skyhighheroes:dyn/stelar_clothes') == 1",
        "SWIMSUIT" : "entity.getData('skyhighheroes:dyn/stelar_clothes') == 2",
        "NORMAL" : "entity.getData('skyhighheroes:dyn/stelar_clothes') == 3"
  },
  
  "animations" : {
    "BLOCKING" : "skyhighheroes:force_field_holding",
    "AIMING" : "skyhighheroes:stelar_aim",
    "fiskheroes:gliding" : "skyhighheroes:stelar_flight"
  }
}